plone.app.theming-6.0.0-py3.13-nspkg.pth
plone/app/theming/__init__.py
plone/app/theming/configure.zcml
plone/app/theming/events.py
plone/app/theming/header.py
plone/app/theming/interfaces.py
plone/app/theming/policy.py
plone/app/theming/testing.py
plone/app/theming/theme.py
plone/app/theming/themes.zcml
plone/app/theming/transform.py
plone/app/theming/traversal.py
plone/app/theming/upgrade.py
plone/app/theming/utils.py
plone/app/theming/zmi.py
plone/app/theming/browser/__init__.py
plone/app/theming/browser/configure.zcml
plone/app/theming/browser/controlpanel.pt
plone/app/theming/browser/controlpanel.py
plone/app/theming/browser/custom_css.py
plone/app/theming/browser/help.py
plone/app/theming/browser/icon.gif
plone/app/theming/browser/theme-error.pt
plone/app/theming/browser/themefile.py
plone/app/theming/browser/resources/controlpanel.css
plone/app/theming/browser/resources/defaultPreview.png
plone/app/theming/browser/resources/preview.png
plone/app/theming/browser/resources/userguide.rst
plone/app/theming/exportimport/__init__.py
plone/app/theming/exportimport/configure.zcml
plone/app/theming/exportimport/handler.py
plone/app/theming/plugins/__init__.py
plone/app/theming/plugins/configure.zcml
plone/app/theming/plugins/hooks.py
plone/app/theming/plugins/utils.py
plone/app/theming/profiles/default/browserlayer.xml
plone/app/theming/profiles/default/controlpanel.xml
plone/app/theming/profiles/default/metadata.xml
plone/app/theming/profiles/default/registry.xml
plone/app/theming/tests/__init__.py
plone/app/theming/tests/browser.py
plone/app/theming/tests/configure.zcml
plone/app/theming/tests/french.html
plone/app/theming/tests/includes.html
plone/app/theming/tests/includes.xml
plone/app/theming/tests/localrules.xml
plone/app/theming/tests/nonascii.html
plone/app/theming/tests/nonascii.xml
plone/app/theming/tests/notheme.pt
plone/app/theming/tests/one.html
plone/app/theming/tests/otherrules.xml
plone/app/theming/tests/othertheme.html
plone_app_theming-6.0.0.dist-info/LICENSE
plone_app_theming-6.0.0.dist-info/METADATA
plone_app_theming-6.0.0.dist-info/WHEEL
plone_app_theming-6.0.0.dist-info/entry_points.txt
plone_app_theming-6.0.0.dist-info/namespace_packages.txt
plone_app_theming-6.0.0.dist-info/top_level.txt
plone_app_theming-6.0.0.dist-info/RECORD
