Metadata-Version: 2.2
Name: plone.app.theming
Version: 6.0.0
Summary: Integrates the Diazo theming engine with Plone
Home-page: https://pypi.org/project/plone.app.theming
Author: Martin Aspeli and Laurence Rowe
Author-email: optilude@gmail.com
License: GPL
Keywords: plone diazo xdv deliverance theme transform xslt
Classifier: Development Status :: 5 - Production/Stable
Classifier: Framework :: Plone
Classifier: Framework :: Plone :: 6.0
Classifier: Framework :: Plone :: Core
Classifier: License :: OSI Approved :: GNU General Public License (GPL)
Classifier: Programming Language :: Python
Classifier: Programming Language :: Python :: 3.8
Classifier: Programming Language :: Python :: 3.9
Classifier: Programming Language :: Python :: 3.10
Classifier: Programming Language :: Python :: 3.11
Classifier: Topic :: Software Development :: Libraries :: Python Modules
Requires-Python: >=3.8
License-File: LICENSE
Requires-Dist: diazo>=1.0.3
Requires-Dist: docutils
Requires-Dist: lxml>=2.2.4
Requires-Dist: plone.app.registry>=1.0
Requires-Dist: plone.base>=3.1.0
Requires-Dist: plone.i18n
Requires-Dist: plone.memoize
Requires-Dist: plone.registry
Requires-Dist: plone.resource
Requires-Dist: plone.resourceeditor>=2.0.0
Requires-Dist: plone.staticresources
Requires-Dist: plone.subrequest
Requires-Dist: plone.transformchain
Requires-Dist: python-dateutil
Requires-Dist: Products.GenericSetup
Requires-Dist: Products.statusmessages
Requires-Dist: repoze.xmliter>=0.3
Requires-Dist: setuptools
Requires-Dist: Zope
Provides-Extra: test
Requires-Dist: plone.app.testing; extra == "test"
Requires-Dist: plone.app.contenttypes[test]; extra == "test"
Requires-Dist: plone.testing; extra == "test"
Dynamic: author
Dynamic: author-email
Dynamic: classifier
Dynamic: description
Dynamic: description-content-type
Dynamic: home-page
Dynamic: keywords
Dynamic: license
Dynamic: provides-extra
Dynamic: requires-dist
Dynamic: requires-python
Dynamic: summary
